[{"id":"aa7796846079e73830bb188717af914ba08c2e55","instances":[{"path":"./jquery-data/1.2.1/src/ajax.js","lines":[391,421],"code":"\t\tjQuery.event.trigger( \"ajaxError\", [xml, s, e] );\n},\n\n// Counter for holding the number of active queries\nactive: 0,\n\n// Determines if an XMLHttpRequest was successful or not\nhttpSuccess: function( r ) {\n\ttry {\n\t\treturn !r.status && location.protocol == \"file:\" ||\n\t\t\t( r.status >= 200 && r.status < 300 ) || r.status == 304 ||\n\t\t\tjQuery.browser.safari && r.status == undefined;\n\t} catch(e){}\n\treturn false;\n},\n\n// Determines if an XMLHttpRequest returns NotModified\nhttpNotModified: function( xml, url ) {\n\ttry {\n\t\tvar xmlRes = xml.getResponseHeader(\"Last-Modified\");\n\n\t\t// Firefox always returns 200. check Last-Modified date\n\t\treturn xml.status == 304 || xmlRes == jQuery.lastModified[url] ||\n\t\t\tjQuery.browser.safari && xml.status == undefined;\n\t} catch(e){}\n\treturn false;\n},\n\nhttpData: function( r, type ) {\n\tvar ct = r.getResponseHeader(\"content-type\");\n\tvar xml = type == \"xml\" || !type && ct && ct.indexOf(\"xml\") >= 0;"},{"path":"./jquery-data/1.0.3/src/ajax/ajax.js","lines":[798,836],"code":"\txml.send(data);\n},\n\n// Counter for holding the number of active queries\nactive: 0,\n\n// Determines if an XMLHttpRequest was successful or not\nhttpSuccess: function(r) {\n\ttry {\n\t\treturn !r.status && location.protocol == \"file:\" ||\n\t\t\t( r.status >= 200 && r.status < 300 ) || r.status == 304 ||\n\t\t\tjQuery.browser.safari && r.status == undefined;\n\t} catch(e){}\n\n\treturn false;\n},\n\n// Determines if an XMLHttpRequest returns NotModified\nhttpNotModified: function(xml, url) {\n\ttry {\n\t\tvar xmlRes = xml.getResponseHeader(\"Last-Modified\");\n\n\t\t// Firefox always returns 200. check Last-Modified date\n\t\treturn xml.status == 304 || xmlRes == jQuery.lastModified[url] ||\n\t\t\tjQuery.browser.safari && xml.status == undefined;\n\t} catch(e){}\n\n\treturn false;\n},\n\n/* Get the data out of an XMLHttpRequest.\n * Return parsed XML if content-type header is \"xml\" and type is \"xml\" or omitted,\n * otherwise return plain text.\n * (String) data - The type of data that you're expecting back,\n * (e.g. \"xml\", \"html\", \"script\")\n */\nhttpData: function(r,type) {\n\tvar ct = r.getResponseHeader(\"content-type\");\n\tvar data = !type && ct && ct.indexOf(\"xml\") >= 0;"}]},
{"id":"47b0539d1098bbe4e46d3667c978ff52c56aa203","instances":[{"path":"./jquery-data/1.2.1/src/core.js","lines":[627,639],"code":"swap: function(e,o,f) {\n\tfor ( var i in o ) {\n\t\te.style[\"old\"+i] = e.style[i];\n\t\te.style[i] = o[i];\n\t}\n\tf.apply( e, [] );\n\tfor ( var i in o )\n\t\te.style[i] = e.style[\"old\"+i];\n},\n\ncss: function(e,p) {\n\tif ( p == \"height\" || p == \"width\" ) {\n\t\tvar old = {}, oHeight, oWidth, d = [\"Top\",\"Bottom\",\"Right\",\"Left\"];"},{"path":"./jquery-data/1.0.3/src/jquery/jquery.js","lines":[1458,1470],"code":"swap: function(e,o,f) {\n\tfor ( var i in o ) {\n\t\te.style[\"old\"+i] = e.style[i];\n\t\te.style[i] = o[i];\n\t}\n\tf.apply( e, [] );\n\tfor ( var i in o )\n\t\te.style[i] = e.style[\"old\"+i];\n},\n\ncss: function(e,p) {\n\tif ( p == \"height\" || p == \"width\" ) {\n\t\tvar old = {}, oHeight, oWidth, d = [\"Top\",\"Bottom\",\"Right\",\"Left\"];"}]},
{"id":"0f4c4328e51d464cd6aa31d60441f813f8a05345","instances":[{"path":"./jquery-data/1.2.1/src/core.js","lines":[647,657],"code":"if ( jQuery(e).is(':visible') ) {\n\toHeight = e.offsetHeight;\n\toWidth = e.offsetWidth;\n} else {\n\te = jQuery(e.cloneNode(true))\n\t\t.find(\":radio\").removeAttr(\"checked\").end()\n\t\t.css({\n\t\t\tvisibility: \"hidden\", position: \"absolute\", display: \"block\", right: \"0\", left: \"0\"\n\t\t}).appendTo(e.parentNode)[0];\n\n\tvar parPos = jQuery.css(e.parentNode,\"position\") || \"static\";"},{"path":"./jquery-data/1.0.3/src/jquery/jquery.js","lines":[1478,1488],"code":"if (jQuery.css(e,\"display\") != \"none\") {\n\toHeight = e.offsetHeight;\n\toWidth = e.offsetWidth;\n} else {\n\te = jQuery(e.cloneNode(true))\n\t\t.find(\":radio\").removeAttr(\"checked\").end()\n\t\t.css({\n\t\t\tvisibility: \"hidden\", position: \"absolute\", display: \"block\", right: \"0\", left: \"0\"\n\t\t}).appendTo(e.parentNode)[0];\n\n\tvar parPos = jQuery.css(e.parentNode,\"position\");"}]}]
