[{"id":"35113d241fcf382b8c318bf5715d7980449dd8ee","instances":[{"path":"./jquery-data/1.12.2/src/effects.js","lines":[408,417],"code":"var opt = speed && typeof speed === \"object\" ? jQuery.extend( {}, speed ) : {\n\tcomplete: fn || !fn && easing ||\n\t\tjQuery.isFunction( speed ) && speed,\n\tduration: speed,\n\teasing: fn && easing || easing && !jQuery.isFunction( easing ) && easing\n};\n\nopt.duration = jQuery.fx.off ? 0 : typeof opt.duration === \"number\" ? opt.duration :\n\topt.duration in jQuery.fx.speeds ?\n\t\tjQuery.fx.speeds[ opt.duration ] : jQuery.fx.speeds._default;"},{"path":"./jquery-data/1.3.1/src/fx.js","lines":[193,201],"code":"var opt = typeof speed === \"object\" ? speed : {\n\tcomplete: fn || !fn && easing ||\n\t\tjQuery.isFunction( speed ) && speed,\n\tduration: speed,\n\teasing: fn && easing || easing && !jQuery.isFunction(easing) && easing\n};\n\nopt.duration = jQuery.fx.off ? 0 : typeof opt.duration === \"number\" ? opt.duration :\n\tjQuery.fx.speeds[opt.duration] || jQuery.fx.speeds._default;"}]},
{"id":"4ebf6afe4a85b6fd504cbb356b0b845aa6628a1e","instances":[{"path":"./jquery-data/1.12.2/src/event.js","lines":[150,158],"code":"types = ( types || \"\" ).match( rnotwhite ) || [ \"\" ];\nt = types.length;\nwhile ( t-- ) {\n\ttmp = rtypenamespace.exec( types[ t ] ) || [];\n\ttype = origType = tmp[ 1 ];\n\tnamespaces = ( tmp[ 2 ] || \"\" ).split( \".\" ).sort();\n\n\t// There *must* be a type, no attaching namespace-only handlers\n\tif ( !type ) {"},{"path":"./jquery-data/1.12.2/src/event.js","lines":[238,246],"code":"types = ( types || \"\" ).match( rnotwhite ) || [ \"\" ];\nt = types.length;\nwhile ( t-- ) {\n\ttmp = rtypenamespace.exec( types[ t ] ) || [];\n\ttype = origType = tmp[ 1 ];\n\tnamespaces = ( tmp[ 2 ] || \"\" ).split( \".\" ).sort();\n\n\t// Unbind all events (on this namespace, if provided) for the element\n\tif ( !type ) {"}]},
{"id":"cb5299dcb3632ed75b2a272e625a741ca97fa0b7","instances":[{"path":"./jquery-data/1.12.2/src/manipulation.js","lines":[427,431],"code":"append: function() {\n\treturn domManip( this, arguments, function( elem ) {\n\t\tif ( this.nodeType === 1 || this.nodeType === 11 || this.nodeType === 9 ) {\n\t\t\tvar target = manipulationTarget( this, elem );\n\t\t\ttarget.appendChild( elem );"},{"path":"./jquery-data/1.12.2/src/manipulation.js","lines":[436,440],"code":"prepend: function() {\n\treturn domManip( this, arguments, function( elem ) {\n\t\tif ( this.nodeType === 1 || this.nodeType === 11 || this.nodeType === 9 ) {\n\t\t\tvar target = manipulationTarget( this, elem );\n\t\t\ttarget.insertBefore( elem, target.firstChild );"}]},
{"id":"1d6345626f8af738033c198710ddb0197160abda","instances":[{"path":"./jquery-data/1.12.2/src/manipulation.js","lines":[558,565],"code":"jQuery.each( {\n\tappendTo: \"append\",\n\tprependTo: \"prepend\",\n\tinsertBefore: \"before\",\n\tinsertAfter: \"after\",\n\treplaceAll: \"replaceWith\"\n}, function( name, original ) {\n\tjQuery.fn[ name ] = function( selector ) {"},{"path":"./jquery-data/1.3.1/src/core.js","lines":[1172,1179],"code":"jQuery.each({\n\tappendTo: \"append\",\n\tprependTo: \"prepend\",\n\tinsertBefore: \"before\",\n\tinsertAfter: \"after\",\n\treplaceAll: \"replaceWith\"\n}, function(name, original){\n\tjQuery.fn[ name ] = function() {"}]},
{"id":"2691372d4fae4363f7385195b0216a31bccfe8b0","instances":[{"path":"./jquery-data/1.12.2/src/serialize.js","lines":[110,116],"code":".map( function( i, elem ) {\n\tvar val = jQuery( this ).val();\n\n\treturn val == null ?\n\t\tnull :\n\t\tjQuery.isArray( val ) ?\n\t\t\tjQuery.map( val, function( val ) {"},{"path":"./jquery-data/1.3.1/src/ajax.js","lines":[76,80],"code":".map(function(i, elem){\n\tvar val = jQuery(this).val();\n\treturn val == null ? null :\n\t\tjQuery.isArray(val) ?\n\t\t\tjQuery.map( val, function(val, i){"}]},
{"id":"f288229d7e06506eed4b3f0438a18d4f5cc075d2","instances":[{"path":"./jquery-data/1.12.2/src/attributes/attr.js","lines":[29,39],"code":"attr: function( elem, name, value ) {\n\tvar ret, hooks,\n\t\tnType = elem.nodeType;\n\n\t// Don't get/set attributes on text, comment and attribute nodes\n\tif ( nType === 3 || nType === 8 || nType === 2 ) {\n\t\treturn;\n\t}\n\n\t// Fallback to prop when attributes are not supported\n\tif ( typeof elem.getAttribute === \"undefined\" ) {"},{"path":"./jquery-data/1.12.2/src/attributes/prop.js","lines":[30,39],"code":"prop: function( elem, name, value ) {\n\tvar ret, hooks,\n\t\tnType = elem.nodeType;\n\n\t// Don't get/set properties on text, comment and attribute nodes\n\tif ( nType === 3 || nType === 8 || nType === 2 ) {\n\t\treturn;\n\t}\n\n\tif ( nType !== 1 || !jQuery.isXMLDoc( elem ) ) {"}]},
{"id":"fa35d943bb563a4d7230fc3e31d0cdb2b7fb96f2","instances":[{"path":"./jquery-data/1.12.2/src/attributes/classes.js","lines":[14,20],"code":"addClass: function( value ) {\n\tvar classes, elem, cur, curValue, clazz, j, finalValue,\n\t\ti = 0;\n\n\tif ( jQuery.isFunction( value ) ) {\n\t\treturn this.each( function( j ) {\n\t\t\tjQuery( this ).addClass( value.call( this, j, getClass( this ) ) );"},{"path":"./jquery-data/1.12.2/src/attributes/classes.js","lines":[52,58],"code":"removeClass: function( value ) {\n\tvar classes, elem, cur, curValue, clazz, j, finalValue,\n\t\ti = 0;\n\n\tif ( jQuery.isFunction( value ) ) {\n\t\treturn this.each( function( j ) {\n\t\t\tjQuery( this ).removeClass( value.call( this, j, getClass( this ) ) );"}]},
{"id":"c80935bb1052c2705c6b2f903ff15d80054ec4d4","instances":[{"path":"./jquery-data/1.12.2/src/attributes/classes.js","lines":[24,34],"code":"if ( typeof value === \"string\" && value ) {\n\tclasses = value.match( rnotwhite ) || [];\n\n\twhile ( ( elem = this[ i++ ] ) ) {\n\t\tcurValue = getClass( elem );\n\t\tcur = elem.nodeType === 1 &&\n\t\t\t( \" \" + curValue + \" \" ).replace( rclass, \" \" );\n\n\t\tif ( cur ) {\n\t\t\tj = 0;\n\t\t\twhile ( ( clazz = classes[ j++ ] ) ) {"},{"path":"./jquery-data/1.12.2/src/attributes/classes.js","lines":[66,78],"code":"if ( typeof value === \"string\" && value ) {\n\tclasses = value.match( rnotwhite ) || [];\n\n\twhile ( ( elem = this[ i++ ] ) ) {\n\t\tcurValue = getClass( elem );\n\n\t\t// This expression is here for better compressibility (see addClass)\n\t\tcur = elem.nodeType === 1 &&\n\t\t\t( \" \" + curValue + \" \" ).replace( rclass, \" \" );\n\n\t\tif ( cur ) {\n\t\t\tj = 0;\n\t\t\twhile ( ( clazz = classes[ j++ ] ) ) {"}]},
{"id":"1dcd253328a774e17e471d328a79a0ae6924893f","instances":[{"path":"./jquery-data/1.3.1/src/fx.js","lines":[292,295],"code":"show: function(){\n\t// Remember where we started, so that we can go back to it later\n\tthis.options.orig[this.prop] = jQuery.attr( this.elem.style, this.prop );\n\tthis.options.show = true;"},{"path":"./jquery-data/1.3.1/src/fx.js","lines":[307,310],"code":"hide: function(){\n\t// Remember where we started, so that we can go back to it later\n\tthis.options.orig[this.prop] = jQuery.attr( this.elem.style, this.prop );\n\tthis.options.hide = true;"}]},
{"id":"a7f641ddc6d6c7e205d915560710a2c2b5c47b37","instances":[{"path":"./jquery-data/1.3.1/src/offset.js","lines":[2,4],"code":"jQuery.fn.offset = function() {\n\tif ( !this[0] ) return { top: 0, left: 0 };\n\tif ( this[0] === this[0].ownerDocument.body ) return jQuery.offset.bodyOffset( this[0] );"},{"path":"./jquery-data/1.3.1/src/offset.js","lines":[12,14],"code":"jQuery.fn.offset = function() {\n\tif ( !this[0] ) return { top: 0, left: 0 };\n\tif ( this[0] === this[0].ownerDocument.body ) return jQuery.offset.bodyOffset( this[0] );"}]},
{"id":"a6c181fcf4ed0c10bb2db452ce5496dfda3035dc","instances":[{"path":"./jquery-data/1.3.1/src/selector.js","lines":[750,757],"code":"function dirNodeCheck( dir, cur, doneName, checkSet, nodeCheck, isXML ) {\n\tfor ( var i = 0, l = checkSet.length; i < l; i++ ) {\n\t\tvar elem = checkSet[i];\n\t\tif ( elem ) {\n\t\t\telem = elem[dir];\n\t\t\tvar match = false;\n\n\t\t\twhile ( elem && elem.nodeType ) {"},{"path":"./jquery-data/1.3.1/src/selector.js","lines":[780,787],"code":"function dirCheck( dir, cur, doneName, checkSet, nodeCheck, isXML ) {\n\tfor ( var i = 0, l = checkSet.length; i < l; i++ ) {\n\t\tvar elem = checkSet[i];\n\t\tif ( elem ) {\n\t\t\telem = elem[dir];\n\t\t\tvar match = false;\n\n\t\t\twhile ( elem && elem.nodeType ) {"}]}]
