[{"id":"5274990d69d3f67676d6aca326b3be3635ce4d9b","instances":[{"path":"./jquery-data/2.1.1/src/wrap.js","lines":[33,60],"code":"\t\t\treturn elem;\n\t\t}).append( this );\n\t}\n\n\treturn this;\n},\n\nwrapInner: function( html ) {\n\tif ( jQuery.isFunction( html ) ) {\n\t\treturn this.each(function( i ) {\n\t\t\tjQuery( this ).wrapInner( html.call(this, i) );\n\t\t});\n\t}\n\n\treturn this.each(function() {\n\t\tvar self = jQuery( this ),\n\t\t\tcontents = self.contents();\n\n\t\tif ( contents.length ) {\n\t\t\tcontents.wrapAll( html );\n\n\t\t} else {\n\t\t\tself.append( html );\n\t\t}\n\t});\n},\n\nwrap: function( html ) {"},{"path":"./jquery-data/1.4.1/src/manipulation.js","lines":[72,98],"code":"\t\t\treturn elem;\n\t\t}).append(this);\n\t}\n\n\treturn this;\n},\n\nwrapInner: function( html ) {\n\tif ( jQuery.isFunction( html ) ) {\n\t\treturn this.each(function(i) {\n\t\t\tjQuery(this).wrapInner( html.call(this, i) );\n\t\t});\n\t}\n\n\treturn this.each(function() {\n\t\tvar self = jQuery( this ), contents = self.contents();\n\n\t\tif ( contents.length ) {\n\t\t\tcontents.wrapAll( html );\n\n\t\t} else {\n\t\t\tself.append( html );\n\t\t}\n\t});\n},\n\nwrap: function( html ) {"}]},
{"id":"d2bf489e1fbbf70423904906e9e34acf048bb828","instances":[{"path":"./jquery-data/2.1.1/src/ajax.js","lines":[526,528],"code":"if ( s.data && s.processData && typeof s.data !== \"string\" ) {\n\ts.data = jQuery.param( s.data, s.traditional );\n}"},{"path":"./jquery-data/1.4.1/src/ajax.js","lines":[213,215],"code":"if ( s.data && s.processData && typeof s.data !== \"string\" ) {\n\ts.data = jQuery.param( s.data, s.traditional );\n}"}]},
{"id":"65d8a8b792bf4313913fa27259900548f1da8ccb","instances":[{"path":"./jquery-data/2.1.1/src/core.js","lines":[146,165],"code":"if ( i === length ) {\n\ttarget = this;\n\ti--;\n}\n\nfor ( ; i < length; i++ ) {\n\t// Only deal with non-null/undefined values\n\tif ( (options = arguments[ i ]) != null ) {\n\t\t// Extend the base object\n\t\tfor ( name in options ) {\n\t\t\tsrc = target[ name ];\n\t\t\tcopy = options[ name ];\n\n\t\t\t// Prevent never-ending loop\n\t\t\tif ( target === copy ) {\n\t\t\t\tcontinue;\n\t\t\t}\n\n\t\t\t// Recurse if we're merging plain objects or arrays\n\t\t\tif ( deep && copy && ( jQuery.isPlainObject(copy) || (copyIsArray = jQuery.isArray(copy)) ) ) {"},{"path":"./jquery-data/1.4.1/src/core.js","lines":[301,320],"code":"if ( length === i ) {\n\ttarget = this;\n\t--i;\n}\n\nfor ( ; i < length; i++ ) {\n\t// Only deal with non-null/undefined values\n\tif ( (options = arguments[ i ]) != null ) {\n\t\t// Extend the base object\n\t\tfor ( name in options ) {\n\t\t\tsrc = target[ name ];\n\t\t\tcopy = options[ name ];\n\n\t\t\t// Prevent never-ending loop\n\t\t\tif ( target === copy ) {\n\t\t\t\tcontinue;\n\t\t\t}\n\n\t\t\t// Recurse if we're merging object literal values or arrays\n\t\t\tif ( deep && copy && ( jQuery.isPlainObject(copy) || jQuery.isArray(copy) ) ) {"}]},
{"id":"35113d241fcf382b8c318bf5715d7980449dd8ee","instances":[{"path":"./jquery-data/2.1.1/src/effects.js","lines":[423,431],"code":"var opt = speed && typeof speed === \"object\" ? jQuery.extend( {}, speed ) : {\n\tcomplete: fn || !fn && easing ||\n\t\tjQuery.isFunction( speed ) && speed,\n\tduration: speed,\n\teasing: fn && easing || easing && !jQuery.isFunction( easing ) && easing\n};\n\nopt.duration = jQuery.fx.off ? 0 : typeof opt.duration === \"number\" ? opt.duration :\n\topt.duration in jQuery.fx.speeds ? jQuery.fx.speeds[ opt.duration ] : jQuery.fx.speeds._default;"},{"path":"./jquery-data/1.4.1/src/effects.js","lines":[239,247],"code":"var opt = speed && typeof speed === \"object\" ? speed : {\n\tcomplete: fn || !fn && easing ||\n\t\tjQuery.isFunction( speed ) && speed,\n\tduration: speed,\n\teasing: fn && easing || easing && !jQuery.isFunction(easing) && easing\n};\n\nopt.duration = jQuery.fx.off ? 0 : typeof opt.duration === \"number\" ? opt.duration :\n\tjQuery.fx.speeds[opt.duration] || jQuery.fx.speeds._default;"}]},
{"id":"4ebf6afe4a85b6fd504cbb356b0b845aa6628a1e","instances":[{"path":"./jquery-data/2.1.1/src/event.js","lines":[81,89],"code":"types = ( types || \"\" ).match( rnotwhite ) || [ \"\" ];\nt = types.length;\nwhile ( t-- ) {\n\ttmp = rtypenamespace.exec( types[t] ) || [];\n\ttype = origType = tmp[1];\n\tnamespaces = ( tmp[2] || \"\" ).split( \".\" ).sort();\n\n\t// There *must* be a type, no attaching namespace-only handlers\n\tif ( !type ) {"},{"path":"./jquery-data/2.1.1/src/event.js","lines":[161,169],"code":"types = ( types || \"\" ).match( rnotwhite ) || [ \"\" ];\nt = types.length;\nwhile ( t-- ) {\n\ttmp = rtypenamespace.exec( types[t] ) || [];\n\ttype = origType = tmp[1];\n\tnamespaces = ( tmp[2] || \"\" ).split( \".\" ).sort();\n\n\t// Unbind all events (on this namespace, if provided) for the element\n\tif ( !type ) {"}]},
{"id":"925f8f4df2e42b0c7a23803463025651bfc288a6","instances":[{"path":"./jquery-data/2.1.1/src/manipulation.js","lines":[324,328],"code":"append: function() {\n\treturn this.domManip( arguments, function( elem ) {\n\t\tif ( this.nodeType === 1 || this.nodeType === 11 || this.nodeType === 9 ) {\n\t\t\tvar target = manipulationTarget( this, elem );\n\t\t\ttarget.appendChild( elem );"},{"path":"./jquery-data/2.1.1/src/manipulation.js","lines":[333,337],"code":"prepend: function() {\n\treturn this.domManip( arguments, function( elem ) {\n\t\tif ( this.nodeType === 1 || this.nodeType === 11 || this.nodeType === 9 ) {\n\t\t\tvar target = manipulationTarget( this, elem );\n\t\t\ttarget.insertBefore( elem, target.firstChild );"}]},
{"id":"fd4e1c9c853e11db1f12e7f324f8d807c12b208c","instances":[{"path":"./jquery-data/2.1.1/src/manipulation.js","lines":[554,562],"code":"jQuery.each({\n\tappendTo: \"append\",\n\tprependTo: \"prepend\",\n\tinsertBefore: \"before\",\n\tinsertAfter: \"after\",\n\treplaceAll: \"replaceWith\"\n}, function( name, original ) {\n\tjQuery.fn[ name ] = function( selector ) {\n\t\tvar elems,"},{"path":"./jquery-data/1.4.1/src/manipulation.js","lines":[375,383],"code":"jQuery.each({\n\tappendTo: \"append\",\n\tprependTo: \"prepend\",\n\tinsertBefore: \"before\",\n\tinsertAfter: \"after\",\n\treplaceAll: \"replaceWith\"\n}, function( name, original ) {\n\tjQuery.fn[ name ] = function( selector ) {\n\t\tvar ret = [], insert = jQuery( selector );"}]},
{"id":"fa9365950c85b61dff915dfa959c2dc50f25b679","instances":[{"path":"./jquery-data/2.1.1/src/selector-native.js","lines":[108,117],"code":"if ( selector_hasDuplicate ) {\n\twhile ( (elem = results[i++]) ) {\n\t\tif ( elem === results[ i ] ) {\n\t\t\tj = duplicates.push( i );\n\t\t}\n\t}\n\twhile ( j-- ) {\n\t\tresults.splice( duplicates[ j ], 1 );\n\t}\n}"},{"path":"./jquery-data/2.1.1/src/sizzle/dist/sizzle.js","lines":[906,915],"code":"if ( hasDuplicate ) {\n\twhile ( (elem = results[i++]) ) {\n\t\tif ( elem === results[ i ] ) {\n\t\t\tj = duplicates.push( i );\n\t\t}\n\t}\n\twhile ( j-- ) {\n\t\tresults.splice( duplicates[ j ], 1 );\n\t}\n}"}]},
{"id":"4f32a1fea583b54dc44613fd06b7151a89cef2ae","instances":[{"path":"./jquery-data/2.1.1/src/selector-native.js","lines":[121,131],"code":"text: function( elem ) {\n\tvar node,\n\t\tret = \"\",\n\t\ti = 0,\n\t\tnodeType = elem.nodeType;\n\n\tif ( !nodeType ) {\n\t\t// If no nodeType, this is expected to be an array\n\t\twhile ( (node = elem[i++]) ) {\n\t\t\t// Do not traverse comment nodes\n\t\t\tret += jQuery.text( node );"},{"path":"./jquery-data/2.1.1/src/sizzle/dist/sizzle.js","lines":[928,938],"code":"getText = Sizzle.getText = function( elem ) {\n\tvar node,\n\t\tret = \"\",\n\t\ti = 0,\n\t\tnodeType = elem.nodeType;\n\n\tif ( !nodeType ) {\n\t\t// If no nodeType, this is expected to be an array\n\t\twhile ( (node = elem[i++]) ) {\n\t\t\t// Do not traverse comment nodes\n\t\t\tret += getText( node );"}]},
{"id":"f3f5e66d41a52315ae8e25a943c75e021479e787","instances":[{"path":"./jquery-data/2.1.1/src/selector-native.js","lines":[143,147],"code":"contains: function( a, b ) {\n\tvar adown = a.nodeType === 9 ? a.documentElement : a,\n\t\tbup = b && b.parentNode;\n\treturn a === bup || !!( bup && bup.nodeType === 1 && adown.contains(bup) );\n},"},{"path":"./jquery-data/2.1.1/src/sizzle/dist/sizzle.js","lines":[701,705],"code":"contains = hasCompare || rnative.test( docElem.contains ) ?\n\tfunction( a, b ) {\n\t\tvar adown = a.nodeType === 9 ? a.documentElement : a,\n\t\t\tbup = b && b.parentNode;\n\t\treturn a === bup || !!( bup && bup.nodeType === 1 && ("}]},
{"id":"2691372d4fae4363f7385195b0216a31bccfe8b0","instances":[{"path":"./jquery-data/2.1.1/src/serialize.js","lines":[96,102],"code":".map(function( i, elem ) {\n\tvar val = jQuery( this ).val();\n\n\treturn val == null ?\n\t\tnull :\n\t\tjQuery.isArray( val ) ?\n\t\t\tjQuery.map( val, function( val ) {"},{"path":"./jquery-data/1.4.1/src/ajax.js","lines":[95,101],"code":".map(function( i, elem ) {\n\tvar val = jQuery(this).val();\n\n\treturn val == null ?\n\t\tnull :\n\t\tjQuery.isArray(val) ?\n\t\t\tjQuery.map( val, function( val, i ) {"}]},
{"id":"f7917b34ef44c9134626f7f4a91c8b2ca05f7878","instances":[{"path":"./jquery-data/2.1.1/src/traversing.js","lines":[133,145],"code":"jQuery.each({\n\tparent: function( elem ) {\n\t\tvar parent = elem.parentNode;\n\t\treturn parent && parent.nodeType !== 11 ? parent : null;\n\t},\n\tparents: function( elem ) {\n\t\treturn jQuery.dir( elem, \"parentNode\" );\n\t},\n\tparentsUntil: function( elem, i, until ) {\n\t\treturn jQuery.dir( elem, \"parentNode\", until );\n\t},\n\tnext: function( elem ) {\n\t\treturn sibling( elem, \"nextSibling\" );"},{"path":"./jquery-data/1.4.1/src/traversing.js","lines":[165,177],"code":"jQuery.each({\n\tparent: function( elem ) {\n\t\tvar parent = elem.parentNode;\n\t\treturn parent && parent.nodeType !== 11 ? parent : null;\n\t},\n\tparents: function( elem ) {\n\t\treturn jQuery.dir( elem, \"parentNode\" );\n\t},\n\tparentsUntil: function( elem, i, until ) {\n\t\treturn jQuery.dir( elem, \"parentNode\", until );\n\t},\n\tnext: function( elem ) {\n\t\treturn jQuery.nth( elem, 2, \"nextSibling\" );"}]},
{"id":"9e68b2e7e4678df0b6e6326b196b14e761358089","instances":[{"path":"./jquery-data/2.1.1/src/wrap.js","lines":[64,74],"code":"\t\tjQuery( this ).wrapAll( isFunction ? html.call(this, i) : html );\n\t});\n},\n\nunwrap: function() {\n\treturn this.parent().each(function() {\n\t\tif ( !jQuery.nodeName( this, \"body\" ) ) {\n\t\t\tjQuery( this ).replaceWith( this.childNodes );\n\t\t}\n\t}).end();\n}"},{"path":"./jquery-data/1.4.1/src/manipulation.js","lines":[100,110],"code":"\t\tjQuery( this ).wrapAll( html );\n\t});\n},\n\nunwrap: function() {\n\treturn this.parent().each(function() {\n\t\tif ( !jQuery.nodeName( this, \"body\" ) ) {\n\t\t\tjQuery( this ).replaceWith( this.childNodes );\n\t\t}\n\t}).end();\n},"}]},
{"id":"c9df5c13bb7ee15e9f5e50d431ba293d4d7f363d","instances":[{"path":"./jquery-data/2.1.1/src/attributes/classes.js","lines":[20,31],"code":"\t\tjQuery( this ).addClass( value.call( this, j, this.className ) );\n\t});\n}\n\nif ( proceed ) {\n\t// The disjunction here is for better compressibility (see removeClass)\n\tclasses = ( value || \"\" ).match( rnotwhite ) || [];\n\n\tfor ( ; i < len; i++ ) {\n\t\telem = this[ i ];\n\t\tcur = elem.nodeType === 1 && ( elem.className ?\n\t\t\t( \" \" + elem.className + \" \" ).replace( rclass, \" \" ) :"},{"path":"./jquery-data/2.1.1/src/attributes/classes.js","lines":[63,73],"code":"\t\tjQuery( this ).removeClass( value.call( this, j, this.className ) );\n\t});\n}\nif ( proceed ) {\n\tclasses = ( value || \"\" ).match( rnotwhite ) || [];\n\n\tfor ( ; i < len; i++ ) {\n\t\telem = this[ i ];\n\t\t// This expression is here for better compressibility (see addClass)\n\t\tcur = elem.nodeType === 1 && ( elem.className ?\n\t\t\t( \" \" + elem.className + \" \" ).replace( rclass, \" \" ) :"}]},
{"id":"cb6d52b7395c0a3329c47a1da1c930a65635ca4e","instances":[{"path":"./jquery-data/2.1.1/src/effects/animatedSelector.js","lines":[5,10],"code":"], function( jQuery ) {\n\njQuery.expr.filters.animated = function( elem ) {\n\treturn jQuery.grep(jQuery.timers, function( fn ) {\n\t\treturn elem === fn.elem;\n\t}).length;"},{"path":"./jquery-data/1.4.1/src/effects.js","lines":[466,472],"code":"if ( jQuery.expr && jQuery.expr.filters ) {\n\tjQuery.expr.filters.animated = function( elem ) {\n\t\treturn jQuery.grep(jQuery.timers, function( fn ) {\n\t\t\treturn elem === fn.elem;\n\t\t}).length;\n\t};\n}"}]},
{"id":"e715059f755554122e48924d7088fc8680794194","instances":[{"path":"./jquery-data/2.1.1/src/queue/delay.js","lines":[9,13],"code":"jQuery.fn.delay = function( time, type ) {\n\ttime = jQuery.fx ? jQuery.fx.speeds[ time ] || time : time;\n\ttype = type || \"fx\";\n\n\treturn this.queue( type, function( next, hooks ) {"},{"path":"./jquery-data/1.4.1/src/queue.js","lines":[75,79],"code":"delay: function( time, type ) {\n\ttime = jQuery.fx ? jQuery.fx.speeds[time] || time : time;\n\ttype = type || \"fx\";\n\n\treturn this.queue( type, function() {"}]},
{"id":"7a199e64926353b47675f1e5683d8c2139ba4f53","instances":[{"path":"./jquery-data/1.4.1/src/attributes.js","lines":[32,38],"code":"if ( value && typeof value === \"string\" ) {\n\tvar classNames = (value || \"\").split( rspace );\n\n\tfor ( var i = 0, l = this.length; i < l; i++ ) {\n\t\tvar elem = this[i];\n\n\t\tif ( elem.nodeType === 1 ) {"},{"path":"./jquery-data/1.4.1/src/attributes.js","lines":[65,71],"code":"if ( (value && typeof value === \"string\") || value === undefined ) {\n\tvar classNames = (value || \"\").split(rspace);\n\n\tfor ( var i = 0, l = this.length; i < l; i++ ) {\n\t\tvar elem = this[i];\n\n\t\tif ( elem.nodeType === 1 && elem.className ) {"}]},
{"id":"620eca1e3ae37fec2f4ba87fdc57a53a3cce4302","instances":[{"path":"./jquery-data/1.4.1/src/data.js","lines":[17,26],"code":"data: function( elem, name, data ) {\n\tif ( elem.nodeName && jQuery.noData[elem.nodeName.toLowerCase()] ) {\n\t\treturn;\n\t}\n\n\telem = elem == window ?\n\t\twindowData :\n\t\telem;\n\n\tvar id = elem[ expando ], cache = jQuery.cache, thisCache;"},{"path":"./jquery-data/1.4.1/src/data.js","lines":[60,69],"code":"removeData: function( elem, name ) {\n\tif ( elem.nodeName && jQuery.noData[elem.nodeName.toLowerCase()] ) {\n\t\treturn;\n\t}\n\n\telem = elem == window ?\n\t\twindowData :\n\t\telem;\n\n\tvar id = elem[ expando ], cache = jQuery.cache, thisCache = cache[ id ];"}]},
{"id":"6515a08f3775a080fb835c826731d8b6dcd3fed5","instances":[{"path":"./jquery-data/1.4.1/src/manipulation.js","lines":[128,131],"code":"before: function() {\n\tif ( this[0] && this[0].parentNode ) {\n\t\treturn this.domManip(arguments, false, function( elem ) {\n\t\t\tthis.parentNode.insertBefore( elem, this );"},{"path":"./jquery-data/1.4.1/src/manipulation.js","lines":[140,143],"code":"after: function() {\n\tif ( this[0] && this[0].parentNode ) {\n\t\treturn this.domManip(arguments, false, function( elem ) {\n\t\t\tthis.parentNode.insertBefore( elem, this.nextSibling );"}]},
{"id":"a885b70a97ce8723e7abe02bf189b919d1a93e40","instances":[{"path":"./jquery-data/1.4.1/src/offset.js","lines":[1,16],"code":"if ( \"getBoundingClientRect\" in document.documentElement ) {\n\tjQuery.fn.offset = function( options ) {\n\t\tvar elem = this[0];\n\n\t\tif ( options ) { \n\t\t\treturn this.each(function( i ) {\n\t\t\t\tjQuery.offset.setOffset( this, options, i );\n\t\t\t});\n\t\t}\n\n\t\tif ( !elem || !elem.ownerDocument ) {\n\t\t\treturn null;\n\t\t}\n\n\t\tif ( elem === elem.ownerDocument.body ) {\n\t\t\treturn jQuery.offset.bodyOffset( elem );"},{"path":"./jquery-data/1.4.1/src/offset.js","lines":[27,42],"code":"} else {\n\tjQuery.fn.offset = function( options ) {\n\t\tvar elem = this[0];\n\n\t\tif ( options ) { \n\t\t\treturn this.each(function( i ) {\n\t\t\t\tjQuery.offset.setOffset( this, options, i );\n\t\t\t});\n\t\t}\n\n\t\tif ( !elem || !elem.ownerDocument ) {\n\t\t\treturn null;\n\t\t}\n\n\t\tif ( elem === elem.ownerDocument.body ) {\n\t\t\treturn jQuery.offset.bodyOffset( elem );"}]}]
