{"header" : {
  "cloc_url"           : "github.com/AlDanial/cloc",
  "cloc_version"       : "1.81",
  "elapsed_seconds"    : 0.0463411808013916,
  "n_files"            : 19,
  "n_lines"            : 7632,
  "files_per_second"   : 410.002500398726,
  "lines_per_second"   : 164691.530686478,
  "report_file"        : "../out/cloc/1.6.4.json"},
"JavaScript" :{
  "nFiles": 19,
  "blank": 1341,
  "comment": 1089,
  "code": 5202},
"SUM": {
  "blank": 1341,
  "comment": 1089,
  "code": 5202,
  "nFiles": 19} }
