{"header" : {
  "cloc_url"           : "github.com/AlDanial/cloc",
  "cloc_version"       : "1.81",
  "elapsed_seconds"    : 0.122840881347656,
  "n_files"            : 101,
  "n_lines"            : 9008,
  "files_per_second"   : 822.201850816719,
  "lines_per_second"   : 73330.6363579902,
  "report_file"        : "../out/cloc/3.1.0.json"},
"JavaScript" :{
  "nFiles": 101,
  "blank": 1662,
  "comment": 1306,
  "code": 6040},
"SUM": {
  "blank": 1662,
  "comment": 1306,
  "code": 6040,
  "nFiles": 101} }
